ml_tutor/__init__.py
ml_tutor/model.py
ml_tutor/classification/__init__.py
ml_tutor/classification/knn.py
ml_tutor/classification/logistic_regression.py
ml_tutor/classification/tree.py
ml_tutor/clustering/__init__.py
ml_tutor/clustering/kmeans.py
ml_tutor/regression/__init__.py
ml_tutor/regression/linear_regression.py
ml_tutor/regression/tree.py
ml_tutor-1.0.1.dist-info/LICENSE
ml_tutor-1.0.1.dist-info/METADATA
ml_tutor-1.0.1.dist-info/WHEEL
ml_tutor-1.0.1.dist-info/top_level.txt
ml_tutor-1.0.1.dist-info/RECORD
